ua2.table3a-0.7.5-py2.7-nspkg.pth
ua2/table3/__init__.py
ua2/table3/bound.py
ua2/table3/column.py
ua2/table3/data.py
ua2/table3/plugin.py
ua2/table3/render.py
ua2/table3/request.py
ua2/table3/settings.py
ua2/table3/table.py
ua2/table3/utils.py
ua2/table3/plugins/__init__.py
ua2/table3/plugins/actions.py
ua2/table3/plugins/filters.py
ua2/table3/plugins/output.py
ua2/table3/plugins/paginator.py
ua2/table3/plugins/quicksearch.py
ua2/table3/plugins/sortable.py
ua2/table3/templates/ua2/table3/category.html
ua2/table3/templates/ua2/table3/dropdown.html
ua2/table3/templates/ua2/table3/header_checkbox.html
ua2/table3/templates/ua2/table3/header_column.html
ua2/table3/templates/ua2/table3/main.html
ua2/table3/templates/ua2/table3/paginator.html
ua2/table3/templates/ua2/table3/post_action.html
ua2/table3/templates/ua2/table3/quicksearch.html
ua2/table3/templatetags/__init__.py
ua2/table3/templatetags/table3.py
ua2.table3a-0.7.5.dist-info/DESCRIPTION.rst
ua2.table3a-0.7.5.dist-info/METADATA
ua2.table3a-0.7.5.dist-info/RECORD
ua2.table3a-0.7.5.dist-info/WHEEL
ua2.table3a-0.7.5.dist-info/eager_resources.txt
ua2.table3a-0.7.5.dist-info/metadata.json
ua2.table3a-0.7.5.dist-info/namespace_packages.txt
ua2.table3a-0.7.5.dist-info/top_level.txt
