Metadata-Version: 2.0
Name: ua2.table3a
Version: 0.7.5
Summary: Alternative package for rendering tables
Home-page: https://bitbucket.org/ua2web/ua2.table3
Author: Alex V. Koval
Author-email: alex@ua2web.com
License: BSD License
Platform: OS Independent
Classifier: Development Status :: 3 - Alpha
Classifier: Intended Audience :: Developers
Classifier: Framework :: Django
Classifier: License :: OSI Approved :: BSD License
Classifier: Operating System :: OS Independent
Classifier: Programming Language :: Python
Classifier: Programming Language :: Python :: 2
Classifier: Programming Language :: Python :: 3
Classifier: Topic :: Internet :: WWW/HTTP :: Dynamic Content
Classifier: Topic :: Software Development
Classifier: Topic :: Software Development :: Libraries
